config/__init__.py
config/asgi.py
config/settings.py
config/urls.py
config/wsgi.py
django_rest_starter_kit-1.21.1.dist-info/LICENSE
django_rest_starter_kit-1.21.1.dist-info/METADATA
django_rest_starter_kit-1.21.1.dist-info/WHEEL
django_rest_starter_kit-1.21.1.dist-info/top_level.txt
django_rest_starter_kit-1.21.1.dist-info/RECORD
