Metadata-Version: 2.1
Name: django-rest-starter-kit
Version: 1.21.1
Summary: Starter kit for Django Rest Framework projects
Home-page: https://github.com/hossainchisty/django-rest-starter-kit
Author: Hossain Chisty
Author-email: hossain.chisty11@gmail.com
License: MIT
Classifier: Framework :: Django
Classifier: Intended Audience :: Developers
Classifier: License :: OSI Approved :: MIT License
Classifier: Programming Language :: Python :: 3
Classifier: Programming Language :: Python :: 3.6
Classifier: Programming Language :: Python :: 3.7
Classifier: Programming Language :: Python :: 3.8
Classifier: Programming Language :: Python :: 3.9
License-File: LICENSE
Requires-Dist: django
Requires-Dist: djangorestframework
Requires-Dist: rest-framework-simplejwt
Requires-Dist: drf-yasg
